pyenvtool/__init__.py
pyenvtool/__main__.py
pyenvtool/cli.py
pyenvtool/pyenv.py
pyenvtool/python.py
pyenvtool/tests/__init__.py
pyenvtool/tests/test_cli.py
pyenvtool/tests/test_delta.py
pyenvtool/tests/test_pyenv.py
pyenvtool/tests/test_python.py
pyenvtool/tests/test_tests.py
pyenvtool-1.0.0.dist-info/METADATA
pyenvtool-1.0.0.dist-info/WHEEL
pyenvtool-1.0.0.dist-info/LICENSE
pyenvtool-1.0.0.dist-info/entry_points.txt
pyenvtool-1.0.0.dist-info/RECORD
